{
  "appInfo" : {
    "build" : "203.7717.56.2031.7935034",
    "buildDate" : "Sun, 21 Nov 2021 00:35:36 -0500",
    "productCode" : "AI",
    "generated" : "Sat, 9 Apr 2022 12:26:43 -0500",
    "os" : "macOS 11.5",
    "runtime" : "AdoptOpenJDK 11.0.11 11.0.11+9"
  },
  "runtimeInfo" : {
    "maxMemory" : 536870912,
    "numberOfProcessors" : 12,
    "maxNumberOfIndexingThreads" : 4,
    "maxSizeOfFileForIntelliSense" : 2560000,
    "maxSizeOfFileForContentLoading" : 20971520
  },
  "projectIndexingHistory" : {
    "projectName" : "PruebasHooks",
    "numberOfFileProviders" : 71,
    "totalNumberOfFiles" : 69986,
    "totalNumberOfUpToDateFiles" : 69986,
    "times" : {
      "totalUpdatingTime" : "1 s 435 ms",
      "pushPropertiesTime" : "2 ms",
      "updatingStart" : "Sat, 9 Apr 2022 12:26:42 -0500",
      "updatingEnd" : "Sat, 9 Apr 2022 12:26:43 -0500",
      "wasInterrupted" : false
    },
    "numberOfIndexingThreads" : 0,
    "totalStatsPerFileType" : [ ],
    "totalStatsPerIndexer" : [ ],
    "fileProviderStatistics" : [ ]
  }
}